gridwxcomp/__init__.py
gridwxcomp/calc_bias_ratios.py
gridwxcomp/ee_download.py
gridwxcomp/interpgdal.py
gridwxcomp/plot.py
gridwxcomp/prep_metadata.py
gridwxcomp/spatial.py
gridwxcomp/util.py
gridwxcomp/env/environment.yml
gridwxcomp/example_data/BedrockCO_Daily_output.xlsx
gridwxcomp/example_data/BluebellUT_Daily_output.xlsx
gridwxcomp/example_data/CastleValleyUT_Daily_output.xlsx
gridwxcomp/example_data/LoaUT_Daily_output.xlsx
gridwxcomp/example_data/Station_Data.txt
gridwxcomp-0.2.1.dist-info/LICENSE.txt
gridwxcomp-0.2.1.dist-info/METADATA
gridwxcomp-0.2.1.dist-info/WHEEL
gridwxcomp-0.2.1.dist-info/top_level.txt
gridwxcomp-0.2.1.dist-info/RECORD
