Metadata-Version: 2.1
Name: gridwxcomp
Version: 0.2.1
Summary: Compare meterological station data to gridded data
Home-page: https://github.com/WSWUP/gridwxcomp
Download-URL: https://github.com/WSWUP/gridwxcomp/archive/v0.1.0.tar.gz
Author: John Volk, Christian Dunkerly, and Chris Pearson
Author-email: john.volk@dri.edu
License: Apache
Platform: Windows
Platform: Linux
Platform: Mac OS X
Classifier: License :: OSI Approved :: Apache Software License
Classifier: Programming Language :: Python :: 3.11
Classifier: Environment :: Console
Classifier: Development Status :: 4 - Beta
Classifier: Topic :: Scientific/Engineering
Classifier: Intended Audience :: Science/Research
License-File: LICENSE.txt
Requires-Dist: bokeh >=1.0.4
Requires-Dist: fiona <1.10.0,>=1.7.13
Requires-Dist: gdal
Requires-Dist: netCDF4
Requires-Dist: numpy >=1.15
Requires-Dist: openpyxl
Requires-Dist: pandas >=0.24
Requires-Dist: rasterstats >=0.13
Requires-Dist: refet >=0.3.7
Requires-Dist: scipy >=1.1.0
Requires-Dist: shapely
Requires-Dist: xlrd >=1.2.0
Requires-Dist: geopandas
Requires-Dist: earthengine-api
Requires-Dist: pyproj
